testtesttesttesttesttesttesttesttesttesttesttesttesttesttesttesttesttesttesttesttesttesttest/__init__.py
testtesttesttesttesttesttesttesttesttesttesttesttesttesttesttesttesttesttesttesttesttesttest/__main__.py
testtesttesttesttesttesttesttesttesttesttesttesttesttesttesttesttesttesttesttesttesttesttest-0.0.2.data/scripts/tests
testtesttesttesttesttesttesttesttesttesttesttesttesttesttesttesttesttesttesttesttesttesttest-0.0.2.dist-info/METADATA
testtesttesttesttesttesttesttesttesttesttesttesttesttesttesttesttesttesttesttesttesttesttest-0.0.2.dist-info/WHEEL
testtesttesttesttesttesttesttesttesttesttesttesttesttesttesttesttesttesttesttesttesttesttest-0.0.2.dist-info/entry_points.txt
testtesttesttesttesttesttesttesttesttesttesttesttesttesttesttesttesttesttesttesttesttesttest-0.0.2.dist-info/top_level.txt
testtesttesttesttesttesttesttesttesttesttesttesttesttesttesttesttesttesttesttesttesttesttest-0.0.2.dist-info/RECORD
